client/__init__.py
client/host_client.py
client/instance_client.py
client/sequence_client.py
scramjet_api_client-1.1.1.dist-info/METADATA
scramjet_api_client-1.1.1.dist-info/WHEEL
scramjet_api_client-1.1.1.dist-info/top_level.txt
scramjet_api_client-1.1.1.dist-info/RECORD
