Metadata-Version: 2.1
Name: scramjet-api-client
Version: 1.1.1
Home-page: https://github.com/scramjetorg/api-client-python/tree/main/client
Author: Scramjet
Author-email: open-source@scramjet.org
Requires-Python: >=3.9,<4.0
Requires-Dist: scramjet-client-utils >=1.1.1
